verbcalc/__init__.py
verbcalc/core/__init__.py
verbcalc/core/calculate.py
verbcalc/core/dispatcher.py
verbcalc/core/translator/__init__.py
verbcalc/core/translator/symbols.py
verbcalc/core/translator/translator.py
verbcalc/data/answers.json
verbcalc/data/phrasings.json
verbcalc/tests/__init__.py
verbcalc/tests/test_answers.py
verbcalc/tests/test_calculating.py
verbcalc/tests/test_dispatcher.py
verbcalc/tests/test_translator.py
verbcalc-1.5.2b0.dist-info/AUTHORS.md
verbcalc-1.5.2b0.dist-info/LICENSE
verbcalc-1.5.2b0.dist-info/METADATA
verbcalc-1.5.2b0.dist-info/WHEEL
verbcalc-1.5.2b0.dist-info/top_level.txt
verbcalc-1.5.2b0.dist-info/RECORD
