Metadata-Version: 2.1
Name: verbcalc
Version: 1.5.2b0
Summary: VerbCalc is a Python library that allows to perform calculations based on human speech.
Home-page: https://github.com/ErykPiasecki07/VerbCalc
Author: Eryk Piasecki
Author-email: da3aab79-4378-4321-a726-67c4bb1f17ea@aleeas.com
License: BSD-3-Clause Licence
Project-URL: Bug Tracker, https://github.com/ErykPiasecki07/VerbCalc/labels/bug
Project-URL: Documentation, https://verbcalc.readthedocs.io
Platform: UNKNOWN
Classifier: Development Status :: 4 - Beta
Classifier: Programming Language :: Python :: 3
Classifier: Intended Audience :: Developers
Classifier: Intended Audience :: Education
Classifier: License :: OSI Approved :: BSD License
Classifier: Natural Language :: English
Classifier: Topic :: Communications
Classifier: Operating System :: OS Independent
Requires-Python: >=3.6
License-File: LICENSE
License-File: AUTHORS.md
